{"prefix":["","home","travis","build","kaizhu256"],"root":{"name":"","relativeName":"","fullName":"/home/travis/build/kaizhu256/","kind":"dir","metrics":{"lines":{"total":4718,"covered":4718,"skipped":0,"pct":100},"statements":{"total":5138,"covered":5138,"skipped":3299,"pct":100},"functions":{"total":1087,"covered":1087,"skipped":732,"pct":100},"branches":{"total":2714,"covered":2714,"skipped":2179,"pct":100}},"parent":null,"children":[{"name":"node-nedb-lite/","relativeName":"node-nedb-lite/","fullName":"/home/travis/build/kaizhu256/node-nedb-lite/","kind":"dir","metrics":{"lines":{"total":4718,"covered":4718,"skipped":0,"pct":100},"statements":{"total":5138,"covered":5138,"skipped":3299,"pct":100},"functions":{"total":1087,"covered":1087,"skipped":732,"pct":100},"branches":{"total":2714,"covered":2714,"skipped":2179,"pct":100}},"parent":"","children":[{"name":"node-nedb-lite/example.js","relativeName":"example.js","fullName":"/home/travis/build/kaizhu256/node-nedb-lite/example.js","kind":"file","metrics":{"lines":{"total":85,"covered":85,"skipped":0,"pct":100},"statements":{"total":85,"covered":85,"skipped":38,"pct":100},"functions":{"total":15,"covered":15,"skipped":5,"pct":100},"branches":{"total":42,"covered":42,"skipped":18,"pct":100}},"parent":"node-nedb-lite/","children":[]},{"name":"node-nedb-lite/index.js","relativeName":"index.js","fullName":"/home/travis/build/kaizhu256/node-nedb-lite/index.js","kind":"file","metrics":{"lines":{"total":4463,"covered":4463,"skipped":0,"pct":100},"statements":{"total":4883,"covered":4883,"skipped":3258,"pct":100},"functions":{"total":1030,"covered":1030,"skipped":727,"pct":100},"branches":{"total":2638,"covered":2638,"skipped":2159,"pct":100}},"parent":"node-nedb-lite/","children":[]},{"name":"node-nedb-lite/test.js","relativeName":"test.js","fullName":"/home/travis/build/kaizhu256/node-nedb-lite/test.js","kind":"file","metrics":{"lines":{"total":170,"covered":170,"skipped":0,"pct":100},"statements":{"total":170,"covered":170,"skipped":3,"pct":100},"functions":{"total":42,"covered":42,"skipped":0,"pct":100},"branches":{"total":34,"covered":34,"skipped":2,"pct":100}},"parent":"node-nedb-lite/","children":[]}]}]}}